llama_index_asimov/_version.py
llama_index_asimov-0.0.1.dist-info/METADATA
llama_index_asimov-0.0.1.dist-info/WHEEL
llama_index_asimov-0.0.1.dist-info/licenses/UNLICENSE
llama_index_asimov-0.0.1.dist-info/RECORD
