Metadata-Version: 2.4
Name: llama-index-asimov
Version: 0.0.1
Summary: LlamaIndex integration with the ASIMOV platform.
Project-URL: Homepage, https://github.com/asimov-platform
Project-URL: Repository, https://github.com/asimov-platform/llama-index-asimov
Project-URL: Changelog, https://github.com/asimov-platform/llama-index-asimov/blob/master/CHANGES.md
Project-URL: Releases, https://github.com/asimov-platform/llama-index-asimov/releases
Project-URL: Issues, https://github.com/asimov-platform/llama-index-asimov/issues
Author-email: ASIMOV Protocol <support@asimov.so>
License-Expression: Unlicense
License-File: UNLICENSE
Requires-Python: >=3.9
Requires-Dist: llama-index-core>=0.12
